pbspy/__about__.py
pbspy/__init__.py
pbspy/gadi.py
pbspy/py.typed
pbspy-0.0.8.dist-info/METADATA
pbspy-0.0.8.dist-info/WHEEL
pbspy-0.0.8.dist-info/licenses/LICENSE
pbspy-0.0.8.dist-info/RECORD
