Metadata-Version: 2.4
Name: pbspy
Version: 0.0.8
Summary: A python package for working with the Portable Batch System (PBS) job scheduler.
Project-URL: Homepage, https://github.com/MaterialsPhysicsANU/pbspy
Project-URL: Issues, https://github.com/MaterialsPhysicsANU/pbspy/issues
Project-URL: Changelog, https://github.com/MaterialsPhysicsANU/pbspy/blob/main/CHANGELOG.md
Project-URL: Documentation, https://MaterialsPhysicsANU.github.io/pbspy/
Author-email: Lachlan Deakin <ljdgit@gmail.com>
License: MIT License
License-File: LICENSE
Classifier: Development Status :: 3 - Alpha
Classifier: Intended Audience :: Developers
Classifier: License :: OSI Approved :: MIT License
Classifier: Operating System :: POSIX :: Linux
Classifier: Programming Language :: Python :: 3
Classifier: Programming Language :: Python :: 3.11
Classifier: Programming Language :: Python :: 3.12
Classifier: Topic :: System :: Distributed Computing
Requires-Python: >=3.11
Requires-Dist: rich~=13.8
